pytest_docker_compose/__init__.py
pytest_dc-3.3.0.dist-info/LICENSE
pytest_dc-3.3.0.dist-info/METADATA
pytest_dc-3.3.0.dist-info/WHEEL
pytest_dc-3.3.0.dist-info/entry_points.txt
pytest_dc-3.3.0.dist-info/top_level.txt
pytest_dc-3.3.0.dist-info/RECORD
